pyfs_message/__init__.py
pyfs_message/message.py
pyfs_message-1.0.2.dist-info/METADATA
pyfs_message-1.0.2.dist-info/WHEEL
pyfs_message-1.0.2.dist-info/top_level.txt
pyfs_message-1.0.2.dist-info/RECORD
